python_quant_lib.cpython-312-x86_64-linux-gnu.so
tests/date/test_tenor.py
tests/date/test_calendar.py
tests/date/__init__.py
tests/core/test_context.py
tests/core/__init__.py
tests/rates/test_bonds.py
tests/rates/test_bond_curves.py
tests/rates/__init__.py
python_quant_lib/.ninja_deps
python_quant_lib/.ninja_log
python_quant_lib/cmake_install.cmake
python_quant_lib/CMakeCache.txt
python_quant_lib/build.ninja
python_quant_lib/src/protos/generated/cmake_install.cmake
python_quant_lib/src/date/cmake_install.cmake
python_quant_lib/src/core/cmake_install.cmake
python_quant_lib/src/rates/cmake_install.cmake
python_quant_lib/external/pybind11/cmake_install.cmake
python_quant_lib/CMakeFiles/rules.ninja
python_quant_lib/CMakeFiles/cmake.check_cache
python_quant_lib/CMakeFiles/CMakeConfigureLog.yaml
python_quant_lib/CMakeFiles/TargetDirectories.txt
python_quant_lib/CMakeFiles/python_quant_lib.dir/src/bindings.cpp.o
python_quant_lib/CMakeFiles/python_quant_lib.dir/src/date/date_bindings.cpp.o
python_quant_lib/CMakeFiles/python_quant_lib.dir/src/date/tenor.cpp.o
python_quant_lib/CMakeFiles/python_quant_lib.dir/src/date/calendar.cpp.o
python_quant_lib/CMakeFiles/python_quant_lib.dir/src/core/core_bindings.cpp.o
python_quant_lib/CMakeFiles/python_quant_lib.dir/src/core/context.cpp.o
python_quant_lib/CMakeFiles/python_quant_lib.dir/src/rates/rates_bindings.cpp.o
python_quant_lib/CMakeFiles/python_quant_lib.dir/src/rates/yield_curve.cpp.o
python_quant_lib/CMakeFiles/python_quant_lib.dir/src/rates/instruments.cpp.o
python_quant_lib/CMakeFiles/python_quant_lib.dir/src/rates/schedules.cpp.o
python_quant_lib/CMakeFiles/3.28.1/CMakeDetermineCompilerABI_C.bin
python_quant_lib/CMakeFiles/3.28.1/CMakeCXXCompiler.cmake
python_quant_lib/CMakeFiles/3.28.1/CMakeCCompiler.cmake
python_quant_lib/CMakeFiles/3.28.1/CMakeSystem.cmake
python_quant_lib/CMakeFiles/3.28.1/CMakeDetermineCompilerABI_CXX.bin
python_quant_lib-0.13.0.dist-info/METADATA
python_quant_lib-0.13.0.dist-info/WHEEL
python_quant_lib-0.13.0.dist-info/top_level.txt
python_quant_lib-0.13.0.dist-info/LICENSE
python_quant_lib-0.13.0.dist-info/RECORD
