Metadata-Version: 2.1
Name: python-quant-lib
Version: 0.13.0
Summary: A Simple Python Quant Lib
Author: Quant136
Author-email: xdc137@gmail.com
Requires-Python: >=3.11
License-File: LICENSE
Requires-Dist: asttokens ==2.4.1
Requires-Dist: auditwheel ==5.4.0
Requires-Dist: black ==23.3.0
Requires-Dist: build ==1.0.3
Requires-Dist: bump2version ==1.0.1
Requires-Dist: bumpversion ==0.6.0
Requires-Dist: certifi ==2023.7.22
Requires-Dist: cffi ==1.16.0
Requires-Dist: charset-normalizer ==3.3.1
Requires-Dist: click ==8.1.3
Requires-Dist: cmake ==3.27.7
Requires-Dist: colorama ==0.4.6
Requires-Dist: comm ==0.2.0
Requires-Dist: contourpy ==1.1.0
Requires-Dist: cryptography ==41.0.7
Requires-Dist: cycler ==0.11.0
Requires-Dist: debugpy ==1.8.0
Requires-Dist: decorator ==5.1.1
Requires-Dist: docutils ==0.20.1
Requires-Dist: executing ==2.0.1
Requires-Dist: fonttools ==4.40.0
Requires-Dist: idna ==3.4
Requires-Dist: importlib-metadata ==6.8.0
Requires-Dist: iniconfig ==2.0.0
Requires-Dist: ipykernel ==6.28.0
Requires-Dist: ipython ==8.19.0
Requires-Dist: jaraco.classes ==3.3.0
Requires-Dist: jedi ==0.19.1
Requires-Dist: jeepney ==0.8.0
Requires-Dist: jupyter-client ==8.6.0
Requires-Dist: jupyter-core ==5.5.1
Requires-Dist: keyring ==24.2.0
Requires-Dist: kiwisolver ==1.4.4
Requires-Dist: markdown-it-py ==3.0.0
Requires-Dist: matplotlib ==3.7.2
Requires-Dist: matplotlib-inline ==0.1.6
Requires-Dist: mdurl ==0.1.2
Requires-Dist: more-itertools ==10.1.0
Requires-Dist: mypy-extensions ==1.0.0
Requires-Dist: nest-asyncio ==1.5.8
Requires-Dist: nh3 ==0.2.14
Requires-Dist: ninja ==1.11.1
Requires-Dist: numpy ==1.24.3
Requires-Dist: packaging ==23.1
Requires-Dist: pandas ==2.0.3
Requires-Dist: parso ==0.8.3
Requires-Dist: pathspec ==0.11.1
Requires-Dist: pexpect ==4.9.0
Requires-Dist: Pillow ==10.0.0
Requires-Dist: pkginfo ==1.9.6
Requires-Dist: platformdirs ==3.5.1
Requires-Dist: pluggy ==1.0.0
Requires-Dist: prompt-toolkit ==3.0.43
Requires-Dist: protobuf ==4.25.1
Requires-Dist: psutil ==5.9.7
Requires-Dist: ptyprocess ==0.7.0
Requires-Dist: pure-eval ==0.2.2
Requires-Dist: pybind11 ==2.11.1
Requires-Dist: pybind11-stubgen ==0.16.2
Requires-Dist: pycparser ==2.21
Requires-Dist: pyelftools ==0.30
Requires-Dist: Pygments ==2.16.1
Requires-Dist: pyparsing ==3.0.9
Requires-Dist: pyproject-hooks ==1.0.0
Requires-Dist: pytest ==7.3.1
Requires-Dist: python-dateutil ==2.8.2
Requires-Dist: python-dotenv ==1.0.0
Requires-Dist: pytz ==2023.3
Requires-Dist: pywin32-ctypes ==0.2.2
Requires-Dist: pyzmq ==25.1.2
Requires-Dist: readme-renderer ==42.0
Requires-Dist: requests ==2.31.0
Requires-Dist: requests-toolbelt ==1.0.0
Requires-Dist: rfc3986 ==2.0.0
Requires-Dist: rich ==13.6.0
Requires-Dist: SecretStorage ==3.3.3
Requires-Dist: six ==1.16.0
Requires-Dist: stack-data ==0.6.3
Requires-Dist: tornado ==6.4
Requires-Dist: traitlets ==5.14.0
Requires-Dist: twine ==4.0.2
Requires-Dist: tzdata ==2023.3
Requires-Dist: urllib3 ==2.0.7
Requires-Dist: wcwidth ==0.2.12
Requires-Dist: zipp ==3.17.0
Provides-Extra: test
Requires-Dist: pytest >=6.0 ; extra == 'test'
